krabby-0.1.16.dist-info/METADATA
krabby-0.1.16.dist-info/WHEEL
krabby-0.1.16.dist-info/entry_points.txt
krabby-0.1.16.dist-info/license_files/LICENSE
krabby/__init__.pyi
krabby/__init__.py
krabby/__main__.py
krabby/krabby.cpython-311-x86_64-linux-gnu.so
krabby-0.1.16.dist-info/RECORD
