Metadata-Version: 2.3
Name: krabby
Version: 0.1.16
Classifier: Programming Language :: Rust
Classifier: Programming Language :: Python :: Implementation :: CPython
Classifier: Programming Language :: Python :: Implementation :: PyPy
Requires-Dist: typer
License-File: LICENSE
Summary: A Flashtext library for Python by Rust
Requires-Python: >=3.8
